ytcomment/__init__.py
ytcomment/src/__init__.py
ytcomment/src/ytcomment.py
ytcomment-0.0.1.dist-info/LICENSE.txt
ytcomment-0.0.1.dist-info/METADATA
ytcomment-0.0.1.dist-info/WHEEL
ytcomment-0.0.1.dist-info/top_level.txt
ytcomment-0.0.1.dist-info/RECORD
